nightskycam_serialization/__init__.py
nightskycam_serialization/command.py
nightskycam_serialization/config.py
nightskycam_serialization/fix.py
nightskycam_serialization/py.typed
nightskycam_serialization/serialize.py
nightskycam_serialization/status.py
nightskycam_serialization/version.py
nightskycam_serialization-0.1.4.dist-info/METADATA
nightskycam_serialization-0.1.4.dist-info/WHEEL
nightskycam_serialization-0.1.4.dist-info/RECORD
