Metadata-Version: 2.4
Name: nightskycam-serialization
Version: 0.1.4
Summary: communication between nightskycam and nightskycam-server
Author: Vincent Berenz
Author-email: vberenz@tuebingen.mpg.de
Requires-Python: >=3.12,<4
Classifier: Programming Language :: Python :: 3
Classifier: Programming Language :: Python :: 3.12
Classifier: Programming Language :: Python :: 3.13
Classifier: Programming Language :: Python :: 3.14
Requires-Dist: nightskyrunner (>=0.1.1,<0.2.0)
